patchutils.py
patchutils_cli.py
patchutils-1.2.0.dist-info/entry_points.txt
patchutils-1.2.0.dist-info/LICENSE
patchutils-1.2.0.dist-info/WHEEL
patchutils-1.2.0.dist-info/METADATA
patchutils-1.2.0.dist-info/RECORD
