Metadata-Version: 2.1
Name: patchutils
Version: 1.2.0
Summary: Work on patches based on files and directories
Home-page: https://github.com/xcodz-dot/patchutils
License: LGPL-2.1 License
Author: xcodz-dot
Author-email: 71920621+xcodz-dot@users.noreply.github.com
Requires-Python: >=3.6,<4.0
Classifier: License :: Other/Proprietary License
Classifier: Programming Language :: Python :: 3
Classifier: Programming Language :: Python :: 3.6
Classifier: Programming Language :: Python :: 3.7
Classifier: Programming Language :: Python :: 3.8
Classifier: Programming Language :: Python :: 3.9
Project-URL: Repository, https://github.com/xcodz-dot/patchutils
